moodle_dev_mcp/__init__.py
moodle_dev_mcp/__main__.py
moodle_dev_mcp/server.py
moodle_dev_mcp-1.0.4.dist-info/METADATA
moodle_dev_mcp-1.0.4.dist-info/WHEEL
moodle_dev_mcp-1.0.4.dist-info/entry_points.txt
moodle_dev_mcp-1.0.4.dist-info/licenses/LICENSE
moodle_dev_mcp-1.0.4.dist-info/RECORD
