Metadata-Version: 2.4
Name: moodle_dev_mcp
Version: 1.0.4
Summary: MCP Server for Moodle Developer Documentation
Project-URL: Homepage, https://github.com/khairu-aqsara/moodle_dev_mcp
Project-URL: Repository, https://github.com/khairu-aqsara/moodle_dev_mcp
Project-URL: Issues, https://github.com/khairu-aqsara/moodle_dev_mcp/issues
Author-email: Khairu Aqsara <wenkhairu@gmail.com>
License-File: LICENSE
Keywords: api,documentation,mcp,moodle
Classifier: Development Status :: 4 - Beta
Classifier: Intended Audience :: Developers
Classifier: License :: OSI Approved :: MIT License
Classifier: Programming Language :: Python :: 3
Classifier: Programming Language :: Python :: 3.10
Classifier: Programming Language :: Python :: 3.11
Classifier: Programming Language :: Python :: 3.12
Classifier: Programming Language :: Python :: 3.13
Requires-Python: >=3.10
Requires-Dist: aiohttp>=3.8.0
Requires-Dist: beautifulsoup4>=4.11.0
Requires-Dist: mcp>=1.0.0
